[
  {
    "id": "8ed4",
    "requester": "fer",
    "email": "dsfsd",
    "labId": "lab-1",
    "startISO": "2025-10-13T08:42",
    "duration": 2,
    "purpose": "dfs",
    "selectedItems": [
      {
        "itemId": "item-1",
        "qty": 1
      }
    ],
    "status": "returned",
    "returnedAt": "2025-10-02T07:38:59.033Z"
  },
  {
    "id": "5b4d",
    "requester": "",
    "email": "",
    "labId": "lab-1",
    "startISO": "",
    "duration": 2,
    "purpose": "",
    "selectedItems": [
      {
        "itemId": "item-1",
        "qty": 1
      },
      {
        "itemId": "item-2",
        "qty": 1
      }
    ],
    "status": "declined"
  }
]
